gradeforge/__init__.py
gradeforge/__main__.py
gradeforge/classes.sql
gradeforge/combine.py
gradeforge/download.py
gradeforge/grades.py
gradeforge/login.py
gradeforge/parse.py
gradeforge/sql.py
gradeforge/utils.py
gradeforge/web/__init__.py
gradeforge/web/app.py
gradeforge/web/apps.py
gradeforge/web/manage.py
gradeforge/web/models.py
gradeforge/web/settings.py
gradeforge/web/urls.py
gradeforge/web/views.py
gradeforge/web/wsgi.py
gradeforge-0.0.1.dist-info/METADATA
gradeforge-0.0.1.dist-info/RECORD
gradeforge-0.0.1.dist-info/WHEEL
gradeforge-0.0.1.dist-info/entry_points.txt
gradeforge-0.0.1.dist-info/top_level.txt
