Metadata-Version: 2.1
Name: gradeforge
Version: 0.0.1
Summary: view available classes for the University of South Carolina
Home-page: https://github.com/jyn514/GradeForge
Author: Joshua Nelson, Brady O'Leary, Charles Daniels, and James Coman
Author-email: jyn514@gmail.com
License: UNKNOWN
Platform: UNKNOWN
Classifier: Development Status :: 2 - Pre-Alpha
Classifier: Environment :: Console
Classifier: Intended Audience :: Developers
Classifier: Intended Audience :: Education
Classifier: Operating System :: OS Independent
Classifier: Programming Language :: Python :: 3 :: Only
Classifier: Topic :: Database
Classifier: License :: OSI Approved :: GNU General Public License v3 (GPLv3)
Requires-Dist: lxml (<=4.2.1)
Requires-Dist: requests
Requires-Dist: flask
Requires-Dist: selenium
Requires-Dist: pandas (<=0.23.0)
Requires-Dist: matplotlib
Requires-Dist: xlsx2csv
Requires-Dist: pylint
